aiogram_pagination/__init__.py
aiogram_pagination/paginator.py
pagination_aiogram3-0.1.1.dist-info/licenses/LICENSE
pagination_aiogram3-0.1.1.dist-info/METADATA
pagination_aiogram3-0.1.1.dist-info/WHEEL
pagination_aiogram3-0.1.1.dist-info/top_level.txt
pagination_aiogram3-0.1.1.dist-info/RECORD
