Metadata-Version: 2.4
Name: pagination-aiogram3
Version: 0.1.1
Summary: A comprehensive pagination system for aiogram inline keyboards with type safety and easy configuration
Author-email: NavesSapnis <veih.work@gmail.com>
License-Expression: MIT
Project-URL: Homepage, https://github.com/NavesSapnis/pagination-aiogram3
Project-URL: Documentation, https://github.com/NavesSapnis/pagination-aiogram3#readme
Project-URL: Repository, https://github.com/NavesSapnis/pagination-aiogram3
Project-URL: Bug Tracker, https://github.com/NavesSapnis/pagination-aiogram3/issues
Keywords: telegram,bot,aiogram,pagination,keyboard
Classifier: Development Status :: 3 - Alpha
Classifier: Intended Audience :: Developers
Classifier: Operating System :: OS Independent
Classifier: Programming Language :: Python :: 3
Classifier: Programming Language :: Python :: 3.8
Classifier: Programming Language :: Python :: 3.9
Classifier: Programming Language :: Python :: 3.10
Classifier: Programming Language :: Python :: 3.11
Classifier: Programming Language :: Python :: 3.12
Classifier: Topic :: Software Development :: Libraries :: Python Modules
Classifier: Topic :: Communications :: Chat
Requires-Python: >=3.8
License-File: LICENSE
Requires-Dist: aiogram>=3.0
Requires-Dist: pydantic>=2.0
Provides-Extra: dev
Requires-Dist: pytest>=7.0.0; extra == "dev"
Requires-Dist: pytest-asyncio>=0.21.0; extra == "dev"
Requires-Dist: black>=22.0.0; extra == "dev"
Requires-Dist: flake8>=5.0.0; extra == "dev"
Requires-Dist: mypy>=1.0.0; extra == "dev"
Dynamic: license-file
